netatmo.py
setup.cfg
setup.py
pynetatmo.egg-info/PKG-INFO
pynetatmo.egg-info/SOURCES.txt
pynetatmo.egg-info/dependency_links.txt
pynetatmo.egg-info/requires.txt
pynetatmo.egg-info/top_level.txt