Metadata-Version: 1.1
Name: pynetatmo
Version: 0.0.13
Summary: Netatmo API wrapper written in Python
Home-page: https://github.com/fabiocody/PyNetatmo.git
Author: Fabio Codiglioni
Author-email: fabiocody@icloud.com
License: MIT
Keywords: netatmo,thermostat
Platform: UNKNOWN
Classifier: Programming Language :: Python :: 3.4
Classifier: Programming Language :: Python :: 3.5
Classifier: Programming Language :: Python :: 3.6
Classifier: Development Status :: 4 - Beta
